pacoteteste/__init__.py
pacoteteste/teste_modulo_1.py
nome_do_pacote-0.1.0.dist-info/METADATA
nome_do_pacote-0.1.0.dist-info/WHEEL
nome_do_pacote-0.1.0.dist-info/top_level.txt
nome_do_pacote-0.1.0.dist-info/RECORD
